{ "compressionlevel":-1,
 "height":12,
 "infinite":false,
 "layers":[
        {
         "data":[417, 418, 418, 418, 418, 418, 418, 418, 418, 418, 418, 418, 418, 418, 418, 418, 418, 418, 418, 418, 418, 418, 418, 419, 0,
            418, 418, 418, 418, 418, 418, 418, 418, 418, 418, 418, 418, 418, 418, 418, 418, 418, 418, 418, 418, 418, 418, 418, 418, 0,
            418, 420, 418, 418, 418, 420, 418, 418, 418, 420, 418, 418, 418, 418, 418, 420, 418, 418, 418, 420, 418, 418, 418, 420, 0,
            418, 418, 422, 418, 418, 418, 418, 418, 418, 418, 418, 418, 418, 418, 418, 418, 418, 418, 418, 418, 418, 418, 418, 418, 0,
            457, 457, 498, 457, 457, 457, 457, 457, 457, 457, 457, 457, 457, 457, 457, 457, 457, 457, 457, 457, 457, 457, 457, 457, 0,
            457, 457, 457, 457, 457, 457, 457, 302, 303, 303, 303, 303, 303, 303, 303, 303, 303, 303, 303, 303, 303, 303, 304, 457, 0,
            498, 457, 457, 457, 498, 457, 457, 341, 342, 342, 342, 342, 342, 342, 342, 342, 342, 342, 342, 342, 342, 342, 343, 457, 493,
            457, 457, 457, 457, 457, 457, 457, 341, 342, 342, 342, 342, 342, 342, 342, 342, 342, 342, 342, 342, 342, 342, 343, 457, 532,
            457, 457, 498, 457, 457, 457, 457, 341, 342, 342, 342, 342, 342, 342, 342, 342, 342, 342, 342, 342, 342, 342, 343, 457, 0,
            457, 457, 457, 457, 457, 457, 457, 380, 381, 381, 381, 381, 381, 381, 381, 381, 381, 381, 381, 381, 381, 381, 382, 457, 0,
            457, 457, 457, 457, 498, 457, 457, 457, 457, 457, 457, 457, 457, 457, 457, 457, 457, 457, 457, 457, 457, 457, 457, 457, 0,
            0, 0, 0, 0, 0, 0, 0, 0, 0, 0, 0, 0, 496, 0, 0, 0, 0, 0, 0, 0, 0, 0, 0, 0, 0],
         "height":12,
         "id":1,
         "name":"ground",
         "opacity":1,
         "type":"tilelayer",
         "visible":true,
         "width":25,
         "x":0,
         "y":0
        }, 
        {
         "data":[0, 0, 0, 0, 0, 0, 0, 0, 0, 0, 0, 0, 0, 0, 0, 0, 0, 0, 0, 0, 0, 0, 0, 0, 0,
            0, 0, 0, 0, 0, 0, 0, 0, 0, 0, 0, 0, 0, 0, 0, 0, 0, 0, 0, 0, 0, 0, 0, 0, 0,
            0, 0, 0, 0, 0, 0, 0, 0, 0, 0, 0, 0, 0, 0, 0, 0, 0, 0, 0, 0, 0, 0, 0, 0, 0,
            0, 0, 0, 0, 0, 0, 0, 0, 0, 0, 0, 0, 0, 0, 0, 350, 0, 0, 0, 0, 0, 0, 0, 350, 0,
            500, 500, 0, 0, 0, 61, 0, 0, 265, 266, 0, 0, 0, 0, 0, 389, 0, 0, 0, 0, 0, 0, 0, 389, 0,
            0, 0, 0, 0, 0, 61, 0, 0, 0, 0, 0, 0, 0, 0, 0, 0, 0, 0, 0, 0, 0, 0, 0, 0, 0,
            0, 0, 0, 0, 0, 61, 0, 0, 0, 0, 0, 0, 0, 0, 0, 0, 0, 0, 0, 0, 0, 0, 0, 0, 0,
            0, 0, 0, 0, 0, 61, 0, 0, 0, 0, 0, 0, 0, 0, 0, 0, 0, 0, 0, 0, 0, 0, 0, 0, 0,
            0, 0, 0, 0, 0, 61, 0, 0, 0, 0, 0, 0, 0, 0, 0, 0, 0, 0, 0, 0, 0, 0, 0, 0, 0,
            0, 0, 0, 0, 0, 61, 0, 0, 0, 0, 0, 0, 0, 0, 0, 0, 0, 0, 0, 0, 0, 0, 0, 0, 0,
            0, 0, 0, 0, 0, 61, 0, 0, 0, 0, 0, 0, 0, 0, 0, 0, 0, 0, 0, 0, 0, 0, 0, 0, 0,
            0, 0, 0, 0, 0, 0, 0, 0, 0, 0, 0, 0, 0, 0, 0, 0, 0, 0, 0, 0, 0, 0, 0, 0, 0],
         "height":12,
         "id":2,
         "name":"furniture",
         "opacity":1,
         "type":"tilelayer",
         "visible":true,
         "width":25,
         "x":0,
         "y":0
        }, 
        {
         "draworder":"topdown",
         "id":4,
         "name":"boundaries",
         "objects":[
                {
                 "height":112,
                 "id":2,
                 "name":"fence",
                 "rotation":0,
                 "type":"",
                 "visible":true,
                 "width":16,
                 "x":80,
                 "y":64
                }, 
                {
                 "height":16,
                 "id":3,
                 "name":"box",
                 "rotation":0,
                 "type":"",
                 "visible":true,
                 "width":32,
                 "x":0,
                 "y":64
                }, 
                {
                 "height":256,
                 "id":4,
                 "name":"wall",
                 "rotation":0,
                 "type":"",
                 "visible":true,
                 "width":32,
                 "x":-32,
                 "y":-32
                }, 
                {
                 "height":256,
                 "id":5,
                 "name":"fortRoom2",
                 "rotation":0,
                 "type":"",
                 "visible":true,
                 "width":32,
                 "x":400,
                 "y":-32
                }, 
                {
                 "height":96,
                 "id":6,
                 "name":"wall",
                 "rotation":0,
                 "type":"",
                 "visible":true,
                 "width":400,
                 "x":0,
                 "y":-32
                }, 
                {
                 "height":32,
                 "id":7,
                 "name":"world4",
                 "rotation":0,
                 "type":"",
                 "visible":true,
                 "width":400,
                 "x":0,
                 "y":192
                }, 
                {
                 "height":32,
                 "id":8,
                 "name":"wall",
                 "rotation":0,
                 "type":"",
                 "visible":true,
                 "width":16,
                 "x":384,
                 "y":64
                }, 
                {
                 "height":48,
                 "id":9,
                 "name":"wall",
                 "rotation":0,
                 "type":"",
                 "visible":true,
                 "width":16,
                 "x":384,
                 "y":128
                }, 
                {
                 "height":16,
                 "id":10,
                 "name":"table",
                 "rotation":0,
                 "type":"",
                 "visible":true,
                 "width":32,
                 "x":128,
                 "y":64
                }, 
                {
                 "height":16,
                 "id":11,
                 "name":"shelf",
                 "rotation":0,
                 "type":"",
                 "visible":true,
                 "width":16,
                 "x":240,
                 "y":64
                }, 
                {
                 "height":16,
                 "id":12,
                 "name":"shelf",
                 "rotation":0,
                 "type":"",
                 "visible":true,
                 "width":16,
                 "x":368,
                 "y":64
                }, 
                {
                 "height":16,
                 "id":13,
                 "name":"wall",
                 "rotation":0,
                 "type":"",
                 "visible":true,
                 "width":192,
                 "x":0,
                 "y":176
                }, 
                {
                 "height":16,
                 "id":14,
                 "name":"wall",
                 "rotation":0,
                 "type":"",
                 "visible":true,
                 "width":192,
                 "x":208,
                 "y":176
                }],
         "opacity":1,
         "type":"objectgroup",
         "visible":true,
         "x":0,
         "y":0
        }, 
        {
         "draworder":"topdown",
         "id":3,
         "name":"spawnPoints",
         "objects":[
                {
                 "height":0,
                 "id":1,
                 "name":"player-world4",
                 "point":true,
                 "rotation":0,
                 "type":"",
                 "visible":true,
                 "width":0,
                 "x":192,
                 "y":144
                }],
         "opacity":1,
         "type":"objectgroup",
         "visible":true,
         "x":0,
         "y":0
        }],
 "nextlayerid":5,
 "nextobjectid":15,
 "orientation":"orthogonal",
 "renderorder":"right-down",
 "tiledversion":"1.11.2",
 "tileheight":16,
 "tilesets":[
        {
         "columns":39,
         "firstgid":1,
         "image":"..\/worldBlocks.png",
         "imageheight":496,
         "imagewidth":624,
         "margin":0,
         "name":"worldBlocks",
         "spacing":0,
         "tilecount":1209,
         "tileheight":16,
         "tilewidth":16
        }, 
        {
         "columns":39,
         "firstgid":1210,
         "image":"..\/..\/..\/Game\/public\/spritesheet.png",
         "imageheight":496,
         "imagewidth":624,
         "margin":0,
         "name":"spritesheet",
         "spacing":0,
         "tilecount":1209,
         "tileheight":16,
         "tilewidth":16
        }],
 "tilewidth":16,
 "type":"map",
 "version":"1.10",
 "width":25
}